aita/.editorconfig
aita/.gitignore
aita/README.md
aita/__init__.py
aita/agent/__init__.py
aita/agent/arrow_agent.py
aita/agent/base.py
aita/agent/factory.py
aita/agent/graph.py
aita/agent/pandas_agent.py
aita/agent/python_agent.py
aita/agent/spark_agent.py
aita/agent/sql.py
aita/agent/utils.py
aita/agent/validator.py
aita/datasource/__init__.py
aita/datasource/base.py
aita/datasource/bigquery.py
aita/datasource/catalog.py
aita/datasource/factory.py
aita/datasource/file.py
aita/datasource/mysql.py
aita/datasource/nosql.py
aita/datasource/postgresql.py
aita/datasource/snowflake.py
aita/datasource/sql.py
aita/datasource/sqlite.py
aita/prompt/ExampleFormatTemplate.py
aita/prompt/ExampleSelectorTemplate.py
aita/prompt/PromptICLTemplate.py
aita/prompt/PromptReprTemplate.py
aita/prompt/__init__.py
aita/prompt/base.py
aita/prompt/enums.py
aita/prompt/prompt_builder.py
aita/prompt/templates/dataset1.json
aita/prompt/templates/dataset2.json
aita/prompt/templates/formatted_data.json
aita/prompt/templates/templates_parser.py
aita/prompt/utils.py
aita/states.py
aita/tool/__init__.py
aita/tool/pandas_tool.py
aita/tool/pyarrow_tool.py
aita/tool/python_tool.py
aita/tool/spark_tool.py
aita/tool/sql_tool.py
aita_lab/__init__.py
aita_lab/aita_lab.py
aita_lab/cli.py
aita_lab/components/__init__.py
aita_lab/components/chat_navbar.py
aita_lab/components/codeeditor.py
aita_lab/components/loading_icon.py
aita_lab/components/modal.py
aita_lab/components/model_selector.py
aita_lab/components/reactflow.py
aita_lab/components/sidebar.py
aita_lab/components/table.py
aita_lab/components/upload.py
aita_lab/pages/__init__.py
aita_lab/pages/agent.py
aita_lab/pages/catalog.py
aita_lab/pages/chat.py
aita_lab/pages/datasource.py
aita_lab/pages/document.py
aita_lab/pages/prompt_template.py
aita_lab/pages/settings.py
aita_lab/pages/tool.py
aita_lab/pages/vector_store.py
aita_lab/states/agent.py
aita_lab/states/base.py
aita_lab/states/catalog.py
aita_lab/states/chat.py
aita_lab/states/datasource.py
aita-0.1.5.dist-info/LICENSE
aita-0.1.5.dist-info/METADATA
aita-0.1.5.dist-info/WHEEL
aita-0.1.5.dist-info/entry_points.txt
aita-0.1.5.dist-info/RECORD
