Metadata-Version: 2.1
Name: aita
Version: 0.1.5
Summary: AI Powered Data Platform
Home-page: https://www.project-aita.com
License: Apache Software License 2.0
Keywords: Artificial Intelligence,Data Analysis,Code Generation
Author: aita
Author-email: contact@project-aita.com
Requires-Python: >=3.9,<4.0
Classifier: Development Status :: 3 - Alpha
Classifier: Intended Audience :: Developers
Classifier: License :: OSI Approved :: Apache Software License
Classifier: License :: Other/Proprietary License
Classifier: Operating System :: OS Independent
Classifier: Programming Language :: Python :: 3
Classifier: Programming Language :: Python :: 3.9
Classifier: Programming Language :: Python :: 3.10
Classifier: Programming Language :: Python :: 3.11
Classifier: Programming Language :: Python :: 3.12
Classifier: Topic :: Software Development :: Libraries :: Python Modules
Provides-Extra: aita-lab
Provides-Extra: dynamodb
Provides-Extra: postgresql
Provides-Extra: pyspark
Provides-Extra: snowflake
Requires-Dist: adbc-driver-postgresql (>=1.0.0,<2.0.0) ; extra == "postgresql"
Requires-Dist: adbc-driver-snowflake (>=1.0.0,<2.0.0) ; extra == "snowflake"
Requires-Dist: adbc-driver-sqlite (>=1.0.0,<2.0.0)
Requires-Dist: amundsen-databuilder (>=7.5.0,<8.0.0)
Requires-Dist: boto3 (>=1.34.122,<2.0.0) ; extra == "dynamodb"
Requires-Dist: findspark (>=2.0.1,<3.0.0) ; extra == "pyspark"
Requires-Dist: ipython (==8.14.0)
Requires-Dist: jupyter-ai-magics (>=2.19.0,<3.0.0)
Requires-Dist: langchain (>=0.2.9,<0.3.0)
Requires-Dist: langchain-openai (>=0.1.7,<0.2.0)
Requires-Dist: langgraph (>=0.1.9,<0.2.0)
Requires-Dist: mock (>=5.1.0,<6.0.0)
Requires-Dist: openai (>=1.33.0,<2.0.0)
Requires-Dist: pandas (>=2.2.2,<3.0.0)
Requires-Dist: pyarrow (>=16.1.0,<17.0.0)
Requires-Dist: pydantic (>=2.7.1,<3.0.0)
Requires-Dist: pyspark (>=3.2.0,<4.0.0) ; extra == "pyspark"
Requires-Dist: typer (>=0.12.3,<0.13.0)
Requires-Dist: types-setuptools (>=70.0.0.20240524,<71.0.0.0)
Project-URL: Repository, https://github.com/project-aita/aita
